Metadata-Version: 2.1
Name: cotproxy
Version: 1.0.0
Summary: Cursor-On-Target Transform Proxy
Home-page: https://github.com/ampledata/cotproxy
Author: Greg Albrecht
Author-email: oss@undef.net
License: Apache License, Version 2.0
Keywords: Cursor On Target,ATAK,TAK,COT
Platform: UNKNOWN
Classifier: Programming Language :: Python
Classifier: License :: OSI Approved :: Apache Software License
Provides-Extra: with_pandas
